drf_fsm/__init__.py
drf_fsm/mixins.py
drf_fsm-1.0.4.dist-info/LICENSE
drf_fsm-1.0.4.dist-info/METADATA
drf_fsm-1.0.4.dist-info/WHEEL
drf_fsm-1.0.4.dist-info/top_level.txt
drf_fsm-1.0.4.dist-info/RECORD
